cognite/air/__init__.py
cognite/air/_admin_config.py
cognite/air/_air_api_url.py
cognite/air/_alert_additions.py
cognite/air/_api.py
cognite/air/_backfilling_api.py
cognite/air/_config.py
cognite/air/_events_api.py
cognite/air/_spaces_api.py
cognite/air/_tasks_api.py
cognite/air/_time_series_api.py
cognite/air/_utils.py
cognite/air/admin.py
cognite/air/alert_utils.py
cognite/air/client.py
cognite/air/constants.py
cognite/air/event_utils.py
cognite/air/ts_utils.py
cognite/air/utils.py
cognite_air_sdk-4.0.0.dist-info/LICENSE
cognite_air_sdk-4.0.0.dist-info/WHEEL
cognite_air_sdk-4.0.0.dist-info/METADATA
cognite_air_sdk-4.0.0.dist-info/RECORD
